housing_pred/__init__.py
housing_pred/ingest_data.py
housing_pred/score.py
housing_pred/train.py
housing_pred_mle-0.0.1.dist-info/LICENSE
housing_pred_mle-0.0.1.dist-info/METADATA
housing_pred_mle-0.0.1.dist-info/WHEEL
housing_pred_mle-0.0.1.dist-info/top_level.txt
housing_pred_mle-0.0.1.dist-info/RECORD
