Metadata-Version: 2.1
Name: housing-pred-mle
Version: 0.0.1
Summary: MLE Training Package
Home-page: https://github.com/abhirup77/mle-training
Author: Abhirup Sahoo
Author-email: abhirup.sahoo@tigeranalytics.com
License: UNKNOWN
Project-URL: Bug Tracker, https://github.com/abhirup77/mle-training/issues
Platform: UNKNOWN
Classifier: Programming Language :: Python :: 3
Classifier: License :: OSI Approved :: MIT License
Classifier: Operating System :: OS Independent
Requires-Python: >=3.6
License-File: LICENSE
